menu_kit/__init__.py
menu_kit/cli.py
menu_kit/core/__init__.py
menu_kit/core/config.py
menu_kit/core/database.py
menu_kit/core/display_mode.py
menu_kit/core/runner.py
menu_kit/menu/__init__.py
menu_kit/menu/base.py
menu_kit/menu/dmenu.py
menu_kit/menu/fuzzel.py
menu_kit/menu/fzf.py
menu_kit/menu/rofi.py
menu_kit/menu/stdout.py
menu_kit/plugins/__init__.py
menu_kit/plugins/base.py
menu_kit/plugins/loader.py
menu_kit/plugins/builtin/__init__.py
menu_kit/plugins/builtin/plugins.py
menu_kit/plugins/builtin/settings.py
menu_kit-0.0.1.dist-info/METADATA
menu_kit-0.0.1.dist-info/WHEEL
menu_kit-0.0.1.dist-info/entry_points.txt
menu_kit-0.0.1.dist-info/licenses/LICENSE
menu_kit-0.0.1.dist-info/RECORD
