Metadata-Version: 2.4
Name: menu-kit
Version: 0.0.1
Summary: A modular, menu-agnostic launcher for Linux
Project-URL: Homepage, https://github.com/markhedleyjones/menu-kit
Project-URL: Repository, https://github.com/markhedleyjones/menu-kit
Project-URL: Issues, https://github.com/markhedleyjones/menu-kit/issues
Author-email: Mark Hedley Jones <mark@markhedleyjones.com>
License-Expression: MIT
License-File: LICENSE
Keywords: dmenu,fuzzel,launcher,linux,menu,rofi
Classifier: Development Status :: 3 - Alpha
Classifier: Environment :: X11 Applications
Classifier: Intended Audience :: End Users/Desktop
Classifier: License :: OSI Approved :: MIT License
Classifier: Operating System :: POSIX :: Linux
Classifier: Programming Language :: Python :: 3
Classifier: Programming Language :: Python :: 3.11
Classifier: Programming Language :: Python :: 3.12
Classifier: Topic :: Desktop Environment
Requires-Python: >=3.11
Provides-Extra: dev
Requires-Dist: mypy>=1.0; extra == 'dev'
Requires-Dist: pytest-cov>=4.0; extra == 'dev'
Requires-Dist: pytest>=8.0; extra == 'dev'
Requires-Dist: ruff>=0.1.0; extra == 'dev'
